x_4357_make_markdown_x/__init__.py
x_4357_make_markdown_x/__init__.pyi
x_4357_make_markdown_x/dummy2.txt
x_4357_make_markdown_x/py.typed
x_4357_make_markdown_x/x_cls_make_markdown_x.py
x_4357_make_markdown_x/x_cls_make_markdown_x.pyi
x_4357_make_markdown_x/dummy/dummy.txt
x_4357_make_markdown_x/dummy/mummy/mummy.txt
x_4357_make_markdown_x/yummy/yummy.txt
x_4357_make_markdown_x-0.20.17.dist-info/METADATA
x_4357_make_markdown_x-0.20.17.dist-info/WHEEL
x_4357_make_markdown_x-0.20.17.dist-info/top_level.txt
x_4357_make_markdown_x-0.20.17.dist-info/RECORD
